<powerpagecomponent powerpagecomponentid="79ec3fe6-8e1b-478b-b7d7-ff0b11e26356">
  <content>{"source":"&lt;div class=\"page-copy\"&gt;\r {% editable page 'adx_copy' type: 'html', liquid: true %}\r&lt;/div&gt;"}</content>
  <iscustomizable>1</iscustomizable>
  <name>Page Copy</name>
  <powerpagecomponenttype>8</powerpagecomponenttype>
  <powerpagesiteid>
    <powerpagesiteid>4f023f1a-413e-46e9-8e0d-11684bf9c62f</powerpagesiteid>
  </powerpagesiteid>
  <statecode>0</statecode>
  <statuscode>1</statuscode>
</powerpagecomponent>